<annotation verified="yes">
	<folder>train_resized</folder>
	<filename>392_png.rf.294f5b8dc181b8c612c8809f93412f29.jpg</filename>
	<path>/home/ramin/DSI/projects/capstone_project/train_resized/392_png.rf.294f5b8dc181b8c612c8809f93412f29.jpg</path>
	<source>
		<database>Unknown</database>
	</source>
	<size>
		<width>416</width>
		<height>416</height>
		<depth>3</depth>
	</size>
	<segmented>0</segmented>
	<object>
		<name>solar_panel</name>
		<pose>Unspecified</pose>
		<truncated>0</truncated>
		<difficult>0</difficult>
		<bndbox>
			<xmin>91</xmin>
			<ymin>155</ymin>
			<xmax>242</xmax>
			<ymax>254</ymax>
		</bndbox>
	</object>
	<object>
		<name>car</name>
		<pose>Unspecified</pose>
		<truncated>0</truncated>
		<difficult>0</difficult>
		<bndbox>
			<xmin>178</xmin>
			<ymin>273</ymin>
			<xmax>219</xmax>
			<ymax>359</ymax>
		</bndbox>
	</object>
	<object>
		<name>car</name>
		<pose>Unspecified</pose>
		<truncated>0</truncated>
		<difficult>0</difficult>
		<bndbox>
			<xmin>316</xmin>
			<ymin>309</ymin>
			<xmax>362</xmax>
			<ymax>390</ymax>
		</bndbox>
	</object>
</annotation>
